foxy_project/__init__.py
foxy_project/__main__.py
foxy_project/_version.py
foxy_project/changelog/__init__.py
foxy_project/changelog/_config.py
foxy_project/changelog/changelog.py
foxy_project/changelog/domain_model.py
foxy_project/changelog/presenter.py
foxy_project/changelog/repository.py
foxy_project/changelog/templates/compact.jinja2
foxy_project/changelog/templates/lastrelease.jinja2
foxy_project/changelog/templates/macros.jinja2
foxy_project/config/__init__.py
foxy_project/config/pyproject_reading.py
foxy_project/config/setuptools.py
foxy_project/config/toml.py
foxy_project/version/__init__.py
foxy_project/version/_config.py
foxy_project/version/version.py
foxy_project/version/version_scheme.py
foxy_project-2.4.1.dist-info/METADATA
foxy_project-2.4.1.dist-info/WHEEL
foxy_project-2.4.1.dist-info/entry_points.txt
foxy_project-2.4.1.dist-info/licenses/LICENSE
foxy_project-2.4.1.dist-info/RECORD
