Metadata-Version: 2.1
Name: foxy-project
Version: 2.4.1
Summary: A tool which generates a changelog and manage version for any git repository using conventional commits specification
Project-URL: Documentation, https://github.com/LeMimit/foxy-project#readme
Project-URL: Issues, https://github.com/LeMimit/foxy-project/issues
Project-URL: Source, https://github.com/LeMimit/foxy-project
Author-email: Michael F Bryan <michaelfbryan@gmail.com>, Ken Mijime <kenaco666@gmail.com>, Fabien Hermitte <email@gmail.com>
License-Expression: MIT
License-File: LICENSE
Keywords: changelog,git
Classifier: Development Status :: 4 - Beta
Classifier: Environment :: Console
Classifier: Intended Audience :: Developers
Classifier: License :: OSI Approved :: MIT License
Classifier: Operating System :: POSIX :: Linux
Classifier: Programming Language :: Python
Classifier: Programming Language :: Python :: 3.8
Classifier: Programming Language :: Python :: 3.9
Classifier: Programming Language :: Python :: 3.10
Classifier: Programming Language :: Python :: 3.11
Classifier: Programming Language :: Python :: 3.12
Classifier: Programming Language :: Python :: Implementation :: CPython
Classifier: Topic :: Software Development :: Build Tools
Classifier: Topic :: Software Development :: Documentation
Requires-Python: >=3.8
Requires-Dist: click==8.1.7
Requires-Dist: gitpython==3.1.14
Requires-Dist: jinja2==3.1.2
Requires-Dist: setuptools-scm==8.0.4
